{
    "title": "Merkel: EU hat mit Ei­ni­gung beim Gipfel Hand­lungs­fähigkeit bewiesen",
    "url": "https://www.bundestag.de/dokumente/textarchiv/2020/kw51-de-regierungsbefragung-812302",
    "text": "befragung bundesregierung merkel eu einigung beim gipfel handlungsfahigkeit bewiesen zustand deutschrussische beziehungen diskussion lieferkettengesetz ausgabe ffp masken fur risikogruppen spektrum themen denkbar breit denen bundeskanzlerin angela merkel cdu mittwoch dezember dritten letzten regierungsbefragung jahr bundestag stellung nahm bevor abgeordneten plenum rede antwort stand merkel eingangsstatement genutzt uber ergebnisse europaischen rate dezember abschluss deutschen euratsprasidentschaft berichtet steiniger einigung beim europaischen rat sei langen verhandlungen gelungen brussel mehrjahrigen finanzrahmen geplanten aufbaufonds bekampfung wirtschaftlichen sozialen folgen pandemie geeinigt erstmals konditionalitatsmechanismus verknupfung eumitteln einhaltung rechtsstaatlicher standard geben merkel zudem staats regierungschefs neues klimaziel fur europaische union geeinigt mindestens prozent staaten aussto treibhausgasen reduzieren verglichen wert sagte merkel bisher ziel minus prozent gelegen einigung sei steinig eu letztlich bewiesen handlungsfahig sei fazit kanzlerin weitere themen treffens seien beziehungen turkei partnerschaft usa sowie andauernden verhandlungen grobritannien uber abkommen fur zeit austritt vereinigten konigreichs eu afd fragt neustart beziehungen russland blick osten lenkte hingegen tino chrupalla kanzlerin wissen strategie bundesregierung fur neustart beziehungen russland aussehe merkel erwiderte sehe neustarts bedurfe hohes kontinuitat dennoch konne daruber hinwegsehen schwerwiegende ereignisse vergangenheit gegeben sagte merkel blick anschlag russischen oppositionellen alexej nawalny attentat kleinen tiergarten berlin spd dringt lieferkettengesetz frank schwabe spd fragte haltung bundeskanzlerin geplanten lieferkettengesetz cducsu spd gesetz fur faire arbeitsbedingungen globalen wirtschaft koalitionsvertrag geeinigt union gebe widerstande minister muller dafur minister altmaier dagegen gesetz legislaturperiode sozialdemokrat wissen merkel parierte gute frage sei fur gesetz erkundige nahezu taglich stand verhandlungen union stehe vereinbarungen koalitionsvertrag gebe eben diskussionen uber ausgestaltung einzelner punkte sei etwa frage zusatzlichen zivilrechtlichen haftung strittig fdp kritisiert chaotische verhaltnisse maskenausgabe christine aschenbergdugnus fdp verwies chaotische verhaltnisse lange schlangen apotheken beim auftakt ausgabe kostenlosen ffp masken merkel wissen kommunikation vorgehensweise abgabe bewerte gerade uber jahrigen extra deswegen rausgehen zuhause bleiben ware besser masken gruppe versenden merkel raumte zweiten schritt januar geplant sei allerdings sei bundesregierung wichtig risikogruppen schnell masken auszustatten art verteilung kurzfristig weihnachten organisieren sei moglich machbar cducsu fragt eufinanzrahmen katrin staffler cducsu lobte einigung mehrjahrigen eufinanzrahmen mammutaufgabe abgeordnete einigung sei frei fur innovative digitale nachhaltige eu merkel staffler erfahren zufrieden finanziellen hinterlegung bereiche sei merkel sagte sei froh deutschen vorschlag groer teil mittel fur klimafinanzierung verwendet solle prozent seien gefordert deutschland uber prozent ausgeben fur digitalisierung sei ebenfalls hoherer betrag vorgesehen fur soziale folgen pandemie gebe posten kanzlerin sowie fur spezielle deutschfranzosische projekte bereichen kunstlichen intelligenz mikroelektronik cloudcomputing wasserstoffstrategie linke fragt vermogensabgabe gesine lotzsch linke fragte hintergrund verabschiedung rekordhaushalts fur kommende jahr wer eigentlich pandemierechnung zahlen einschnitte sozialen bereich geben planen vermogenden millionare starker heranzuziehen erkundigte abgeordnete merkel verneinte beides hauptaufgabe sei fur neues wachstum wirtschaft sorgen daruber lieen mehr einnahmen generieren vermogensabgabe geben einschnitte sozialausgaben seien geplant stellte merkel klar grune fragen dezemberhilfen fur unternehmen anja hajduk bundnis die grunen machte darauf aufmerksam unternehmen ab dezember zwang betriebsschlieungen betroffen seien umsatz orientierten dezemberhilfe bekamen beispiel gastronomiebetriebe bereits seit lockdown light november geschlossen unternehmen etwa friseure dicht mussten konnten fur gleiche manahme fixkostenhilfe beantragen monierte hajduk rechtfertigen ungleichbehandlung fuhrt groen ungerechtigkeiten merkel antwortete gebe unterschiedlich betroffene unternehmen wer einschnitte dezember umsatzeinbruch mehr prozent erlebe uberbruckungshilfe iii anspruch mechanismus november dezemberhilfe kombination glauben instrument geschaffen nachhaltig gerecht beginn regierungsbefragung bundestag stimmen afdfraktion tagesordnungen fur dezember beschlossen nachdem zuvor fraktionen daruber einvernehmen hergestellt konnte sas startseite reden tagesordnungspunkt bildinformationen wolfgang schauble wolfgang schauble laurence chaperon schauble wolfgang bundestagsprasident bildinformationen cdu dominik butzmann merkel angela bundeskanzlerin bildinformationen wolfgang schauble wolfgang schauble laurence chaperon schauble wolfgang bundestagsprasident dokumente fundstelle plenarprotokoll tagesordnung sitzungsverlauf weitere informationen gebardensprachvideo ut herausgeber deutscher bundestag onlinedienste startseite",
    "date": "16. Dezember 2020",
    "author": null,
    "links": [
        {
            "title": "zur Startseite",
            "url": "https://www.bundestag.de/"
        },
        {
            "title": "BildinformationenDr. Wolfgang Schäuble© Dr. Wolfgang Schäuble/ Laurence ChaperonSchäuble, Dr. WolfgangBundestagspräsident",
            "url": "https://www.bundestag.de/mediathek?videoid=7490569#url=L21lZGlhdGhla292ZXJsYXk=&mod=mod536668"
        },
        {
            "title": "Bildinformationen© CDU/ Dominik ButzmannMerkel, Dr. AngelaBundeskanzlerin",
            "url": "https://www.bundestag.de/mediathek?videoid=7490572#url=L21lZGlhdGhla292ZXJsYXk=&mod=mod536668"
        },
        {
            "title": "BildinformationenDr. Wolfgang Schäuble© Dr. Wolfgang Schäuble/ Laurence ChaperonSchäuble, Dr. WolfgangBundestagspräsident",
            "url": "https://www.bundestag.de/mediathek?videoid=7490573#url=L21lZGlhdGhla292ZXJsYXk=&mod=mod536668"
        },
        {
            "title": "Fundstelle\nim\nPlenarprotokoll",
            "url": "https://dipbt.bundestag.de/dip21/btp/19/19201.pdf#P.25196"
        },
        {
            "title": "Sitzungsverlauf",
            "url": "https://www.bundestag.de/tagesordnung?week=51&year=2020"
        },
        {
            "title": "Gebärdensprachvideo (mit UT)",
            "url": "https://www.bundestag.de/mediathek?videoid=7490570#url=L21lZGlhdGhla292ZXJsYXk=&mod=mod536668"
        },
        {
            "title": "Deutscher Bundestag, Online-Dienste",
            "url": "https://www.bundestag.de/services/impressum/impressum-196472"
        },
        {
            "title": "zur Startseite",
            "url": "https://www.bundestag.de/"
        }
    ],
    "images": [
        {
            "title": "Dr. Wolfgang Schäuble",
            "url": "https://www.bundestag.de/resource/blob/451034/0de3fbe475aa4210e50d850245ac3c47/Image3x4_small.png"
        },
        {
            "title": "Dr. Angela Merkel",
            "url": "https://www.bundestag.de/resource/blob/451034/0de3fbe475aa4210e50d850245ac3c47/Image3x4_small.png"
        },
        {
            "title": "Dr. Wolfgang Schäuble",
            "url": "https://www.bundestag.de/resource/blob/451034/0de3fbe475aa4210e50d850245ac3c47/Image3x4_small.png"
        }
    ]
}